CHANGES.txt
CONTRIBUTORS.txt
MANIFEST.in
README.txt
setup.py
c2/__init__.py
c2.recipe.bkups3.egg-info/PKG-INFO
c2.recipe.bkups3.egg-info/SOURCES.txt
c2.recipe.bkups3.egg-info/dependency_links.txt
c2.recipe.bkups3.egg-info/entry_points.txt
c2.recipe.bkups3.egg-info/namespace_packages.txt
c2.recipe.bkups3.egg-info/not-zip-safe
c2.recipe.bkups3.egg-info/requires.txt
c2.recipe.bkups3.egg-info/top_level.txt
c2/recipe/__init__.py
c2/recipe/bkups3/README.txt
c2/recipe/bkups3/__init__.py
c2/recipe/bkups3/backuprunner.py
c2/recipe/bkups3/tests/__init__.py
c2/recipe/bkups3/tests/test_docs.py