Metadata-Version: 1.0
Name: c2.recipe.bkups3
Version: 1.1b1
Summary: This recipe is backup for Plone data and send to Amazon S3
Home-page: http://www.cmscom.jp
Author: Manabu TERADA
Author-email: terada@cmscom.jp
License: GPL
Keywords: plone backup recipe blob s3
Platform: UNKNOWN
Classifier: Framework :: Buildout :: Recipe
Classifier: Intended Audience :: Developers
Classifier: Topic :: Software Development :: Build Tools
Classifier: License :: OSI Approved :: GNU General Public License (GPL)
